{
  "frame_size": { "width": 16, "height": 16 },
  "structure": "grid",
  "elements": {
    "BorderLand1": { "x": 0, "y": 0 },
    "BorderLand2": { "x": 0, "y": 1 },
    "BorderDirt1": { "x": 0, "y": 2 },
    "DeepDirt1": { "x": 0, "y": 3 },
    "DeepDirtCorner1": { "x": 0, "y": 4 },
    "InfectedLand1": { "x": 0, "y": 5 },
    "DeepWater1": { "x": 0, "y": 6 },
    "Land1": { "x": 1, "y": 0 },
    "Land2": { "x": 1, "y": 1 },
    "Dirt1": { "x": 1, "y": 2 },
    "DeepDirt2": { "x": 1, "y": 3 },
    "DeepDirtCorner2": { "x": 1, "y": 4 },
    "InfectedLand2": { "x": 1, "y": 5 },
    "DeepWater2": { "x": 1, "y": 6 },
    "Land3": { "x": 2, "y": 0 },
    "Land4": { "x": 2, "y": 1 },
    "Dirt2": { "x": 2, "y": 2 },
    "DeepDirt3": { "x": 2, "y": 3 },
    "CornerLand1": { "x": 2, "y": 4 },
    "InfectedLand3": { "x": 2, "y": 5 },
    "DeepWater3": { "x": 2, "y": 6 },
    "Land5": { "x": 3, "y": 0 },
    "Land6": { "x": 3, "y": 1 },
    "Dirt3": { "x": 3, "y": 2 },
    "CornerLand2": { "x": 3, "y": 3 },
    "CornerLand3": { "x": 3, "y": 4 },
    "InfectedLand4": { "x": 3, "y": 5 },
    "Land7": { "x": 4, "y": 0 },
    "Land8": { "x": 4, "y": 1 },
    "Dirt4": { "x": 4, "y": 2 },
    "CornerLand4": { "x": 4, "y": 3 },
    "SideLand1": { "x": 4, "y": 4 },
    "InfectedLand5": { "x": 4, "y": 5 },
    "Land9": { "x": 5, "y": 0 },
    "Land10": { "x": 5, "y": 1 },
    "Dirt5": { "x": 5, "y": 2 },
    "SideLand2": { "x": 5, "y": 3 },
    "SideLand3": { "x": 5, "y": 4 },
    "InfectedLand6": { "x": 5, "y": 5 },
    "Land11": { "x": 6, "y": 0 },
    "Land12": { "x": 6, "y": 1 },
    "Dirt6": { "x": 6, "y": 2 },
    "SideLand4": { "x": 6, "y": 3 },
    "EdgeLand1": { "x": 6, "y": 4 },
    "Water1": { "x": 6, "y": 5 },
    "Land13": { "x": 7, "y": 0 },
    "Land14": { "x": 7, "y": 1 },
    "Dirt7": { "x": 7, "y": 2 },
    "EdgeLand2": { "x": 7, "y": 3 },
    "EdgeLand3": { "x": 7, "y": 4 },
    "Water2": { "x": 7, "y": 5 },
    "CornerLand5": { "x": 8, "y": 0 },
    "CornerLand6": { "x": 8, "y": 1 },
    "BorderDirt2": { "x": 8, "y": 2 },
    "EdgeLand4": { "x": 8, "y": 3 },
    "InfectedLand7": { "x": 8, "y": 4 },
    "Water3": { "x": 8, "y": 5 }
  }
}